fastapi_jwk_auth/__init__.py
fastapi_jwk_auth/config.py
fastapi_jwk_auth/jwks_auth.py
fastapi_jwk_auth-0.0.5.dist-info/LICENSE
fastapi_jwk_auth-0.0.5.dist-info/METADATA
fastapi_jwk_auth-0.0.5.dist-info/WHEEL
fastapi_jwk_auth-0.0.5.dist-info/top_level.txt
fastapi_jwk_auth-0.0.5.dist-info/RECORD
