Metadata-Version: 2.1
Name: fastapi-jwk-auth
Version: 0.0.5
License: MIT
Project-URL: Source, https://github.com/omkardarves/fastapi-jwk-auth
License-File: LICENSE
Requires-Dist: fastapi
Requires-Dist: PyJWT
Requires-Dist: cryptography
